etlutils/__init__.py
etlutils/datafiles.py
etlutils/date.py
etlutils-0.2.2.dist-info/LICENSE.txt
etlutils-0.2.2.dist-info/METADATA
etlutils-0.2.2.dist-info/WHEEL
etlutils-0.2.2.dist-info/top_level.txt
etlutils-0.2.2.dist-info/RECORD
