Metadata-Version: 2.1
Name: etlutils
Version: 0.2.2
Summary: utilities functions for etl projects
Home-page: https://github.com/kevingoldsmith/etlutils
Author: Kevin Goldsmith
Author-email: github@kevingoldsmith.com
License: MIT
Project-URL: Source, https://github.com/kevingoldsmith/etlutils
Keywords: development etl extract transform load
Platform: UNKNOWN
Classifier: Development Status :: 2 - Pre-Alpha
Classifier: Intended Audience :: Developers
Classifier: Natural Language :: English
Classifier: Topic :: Utilities
Classifier: License :: OSI Approved :: MIT License
Classifier: Programming Language :: Python :: 3.6
Classifier: Programming Language :: Python :: 3.7
Classifier: Programming Language :: Python :: 3.8
Classifier: Programming Language :: Python :: 3.9
Requires-Python: >=3.6
Requires-Dist: python-dateutil (>=2.8.1)
